Metadata-Version: 2.1
Name: marearts-myapp
Version: 1.0.51
Summary: A short description of your application
Home-page: https://github.com/MareArts/pypi_test
Author: MareArts
Author-email: hello@marearts.com
License: MIT
Classifier: Programming Language :: Python :: 3
Classifier: License :: OSI Approved :: MIT License
Classifier: Operating System :: OS Independent
Requires-Python: >=3.8
Requires-Dist: cython>=0.29.21
Requires-Dist: numpy
Requires-Dist: pandas
